dask_sql-2024.5.0.dist-info/METADATA
dask_sql-2024.5.0.dist-info/WHEEL
dask_sql-2024.5.0.dist-info/entry_points.txt
dask_sql-2024.5.0.dist-info/license_files/LICENSE.txt
dask_sql/cmd.py
dask_sql/config.py
dask_sql/context.py
dask_sql/datacontainer.py
dask_sql/input_utils/base.py
dask_sql/input_utils/convert.py
dask_sql/input_utils/dask.py
dask_sql/input_utils/hive.py
dask_sql/input_utils/intake.py
dask_sql/input_utils/location.py
dask_sql/input_utils/pandaslike.py
dask_sql/input_utils/sqlalchemy.py
dask_sql/input_utils/__init__.py
dask_sql/integrations/fugue.py
dask_sql/integrations/ipython.py
dask_sql/integrations/__init__.py
dask_sql/mappings.py
dask_sql/physical/rel/base.py
dask_sql/physical/rel/convert.py
dask_sql/physical/rel/custom/alter.py
dask_sql/physical/rel/custom/analyze_table.py
dask_sql/physical/rel/custom/create_catalog_schema.py
dask_sql/physical/rel/custom/create_experiment.py
dask_sql/physical/rel/custom/create_memory_table.py
dask_sql/physical/rel/custom/create_model.py
dask_sql/physical/rel/custom/create_table.py
dask_sql/physical/rel/custom/describe_model.py
dask_sql/physical/rel/custom/distributeby.py
dask_sql/physical/rel/custom/drop_model.py
dask_sql/physical/rel/custom/drop_schema.py
dask_sql/physical/rel/custom/drop_table.py
dask_sql/physical/rel/custom/export_model.py
dask_sql/physical/rel/custom/metrics.py
dask_sql/physical/rel/custom/predict_model.py
dask_sql/physical/rel/custom/show_columns.py
dask_sql/physical/rel/custom/show_models.py
dask_sql/physical/rel/custom/show_schemas.py
dask_sql/physical/rel/custom/show_tables.py
dask_sql/physical/rel/custom/use_schema.py
dask_sql/physical/rel/custom/wrappers.py
dask_sql/physical/rel/custom/__init__.py
dask_sql/physical/rel/logical/aggregate.py
dask_sql/physical/rel/logical/cross_join.py
dask_sql/physical/rel/logical/empty.py
dask_sql/physical/rel/logical/explain.py
dask_sql/physical/rel/logical/filter.py
dask_sql/physical/rel/logical/join.py
dask_sql/physical/rel/logical/limit.py
dask_sql/physical/rel/logical/project.py
dask_sql/physical/rel/logical/sample.py
dask_sql/physical/rel/logical/sort.py
dask_sql/physical/rel/logical/subquery_alias.py
dask_sql-2024.5.0.dist-info/RECORD
