Metadata-Version: 2.1
Name: dask_sql
Version: 2024.5.0
Classifier: Development Status :: 5 - Production/Stable
Classifier: Intended Audience :: Developers
Classifier: Intended Audience :: Science/Research
Classifier: License :: OSI Approved :: MIT License
Classifier: Operating System :: OS Independent
Classifier: Programming Language :: Rust
Classifier: Programming Language :: Python
Classifier: Programming Language :: Python :: 3
Classifier: Programming Language :: Python :: 3 :: Only
Classifier: Programming Language :: Python :: 3.9
Classifier: Programming Language :: Python :: 3.10
Classifier: Programming Language :: Python :: 3.11
Classifier: Programming Language :: Python :: 3.12
Classifier: Topic :: Scientific/Engineering
Classifier: Topic :: System :: Distributed Computing
Requires-Dist: dask[dataframe] >=2024.4.1
Requires-Dist: distributed >=2024.4.1
Requires-Dist: pandas >=1.4.0
Requires-Dist: fastapi >=0.92.0
Requires-Dist: httpx >=0.24.1
Requires-Dist: uvicorn >=0.14
Requires-Dist: tzlocal >=2.1
Requires-Dist: prompt_toolkit >=3.0.8
Requires-Dist: pygments >=2.7.1
Requires-Dist: tabulate
Requires-Dist: pytest >=6.0.1 ; extra == 'dev'
Requires-Dist: pytest-cov >=2.10.1 ; extra == 'dev'
Requires-Dist: mock >=4.0.3 ; extra == 'dev'
Requires-Dist: sphinx >=3.2.1 ; extra == 'dev'
Requires-Dist: pyarrow >=14.0.1 ; extra == 'dev'
Requires-Dist: scikit-learn >=1.0.0 ; extra == 'dev'
Requires-Dist: intake >=0.6.0 ; extra == 'dev'
Requires-Dist: pre-commit ; extra == 'dev'
Requires-Dist: black ==22.10.0 ; extra == 'dev'
Requires-Dist: isort ==5.12.0 ; extra == 'dev'
Requires-Dist: fugue >=0.7.3 ; extra == 'fugue'
Requires-Dist: triad <0.9.2 ; extra == 'fugue'
Provides-Extra: dev
Provides-Extra: fugue
License-File: LICENSE.txt
Summary: SQL query layer for Dask
Maintainer-email: Nils Braun <nilslennartbraun@gmail.com>
License: MIT
Requires-Python: >=3.9
Project-URL: Homepage, https://github.com/dask-contrib/dask-sql
Project-URL: Documentation, https://dask-sql.readthedocs.io
Project-URL: Source, https://github.com/dask-contrib/dask-sql
